{
  "$schema": "https://schema.management.azure.com/schemas/2015-01-01/deploymentTemplate.json#",
  "contentVersion": "1.0.0.0",
  "parameters": {
    "logicAppName": {
      "type": "string",
      "minLength": 1,
      "maxLength": 80,
      "metadata": {
        "description": "Name of the Logic App."
      }
    },
    "passwordParam": {
      "type": "securestring"
    },
    "urlParam": {
      "type": "string"
    },
    "usernameParam": {
      "type": "securestring"
    },
    "logicAppLocation": {
      "type": "string",
      "defaultValue": "[resourceGroup().location]",
      "allowedValues": [
        "[resourceGroup().location]",
        "eastasia",
        "southeastasia",
        "centralus",
        "eastus",
        "eastus2",
        "westus",
        "northcentralus",
        "southcentralus",
        "northeurope",
        "westeurope",
        "japanwest",
        "japaneast",
        "brazilsouth",
        "australiaeast",
        "australiasoutheast",
        "southindia",
        "centralindia",
        "westindia",
        "canadacentral",
        "canadaeast",
        "uksouth",
        "ukwest",
        "westcentralus",
        "westus2",
        "koreacentral",
        "koreasouth",
        "francecentral",
        "francesouth",
        "southafricanorth",
        "southafricawest"
      ],
      "metadata": {
        "description": "Location of the Logic App."
      }
    }
  },
  "variables": {},
  "resources": [
    {
      "name": "[parameters('logicAppName')]",
      "type": "Microsoft.Logic/workflows",
      "location": "[parameters('logicAppLocation')]",
      "tags": {
        "displayName": "LogicApp"
      },
      "apiVersion": "2016-06-01",
      "properties": {
        "definition": {
          "$schema": "https://schema.management.azure.com/providers/Microsoft.Logic/schemas/2016-06-01/workflowdefinition.json#",
          "actions": {
            "Response": {
              "type": "Response",
              "kind": "http",
              "inputs": {
                "statusCode": "@outputs('HTTP_小reate_order')['statusCode']",
                "body": "@body('HTTP_小reate_order')"
              },
              "runAfter": {
                "HTTP_小reate_order": [
                  "Succeeded"
                ]
              }
            },
            "HTTP_小reate_order": {
              "type": "Http",
              "inputs": {
                "method": "post",
                "uri": "@{concat(parameters('endpointUrl'),'api/order/customerOrders')}",
                "headers": {
                  "Authorization": "Bearer@{body('Parse_token_JSON')?['access_token']} "
                },
                "body": {
                  "createdDate": "@triggerBody()?['createdDate']",
                  "currency": "@triggerBody()?['currency']",
                  "customerId": "@triggerBody()?['customerId']",
                  "customerName": "@triggerBody()?['customerName']",
                  "dynamicProperties": "@triggerBody()?['dynamicProperties']",
                  "items": "@triggerBody()?['items']",
                  "number": "@triggerBody()?['number']",
                  "status": "@triggerBody()?['status']",
                  "storeId": "@triggerBody()?['StoreId']"
                }
              },
              "runAfter": {
                "Parse_token_JSON": [
                  "Succeeded"
                ]
              }
            },
            "HTTP_get_token": {
              "type": "Http",
              "inputs": {
                "method": "POST",
                "uri": "@{concat(parameters('endpointUrl'),'connect/token')}",
                "headers": {
                  "Content-Type": "application/x-www-form-urlencoded"
                },
                "body": "@{encodeUriComponent(concat('grant_type=password&password=',parameters('endpointPassword'),'&username=',parameters('endpointUsername')))}"
              },
              "runAfter": {}
            },
            "Parse_token_JSON": {
              "type": "ParseJson",
              "inputs": {
                "content": "@body('HTTP_get_token')",
                "schema": {
                  "type": "object",
                  "properties": {
                    "token_type": {
                      "type": "string"
                    },
                    "access_token": {
                      "type": "string"
                    },
                    "expires_in": {
                      "type": "integer"
                    }
                  }
                }
              },
              "runAfter": {
                "HTTP_get_token": [
                  "Succeeded"
                ]
              }
            }
          },
          "parameters": {
            "endpointPassword": {
              "defaultValue": "aA111111",
              "type": "securestring"
            },
            "endpointUrl": {
              "defaultValue": "https://dev-odt-admin.azurewebsites.net/",
              "type": "string"
            },
            "endpointUsername": {
              "defaultValue": "integration",
              "type": "securestring"
            }
          },
          "triggers": {
            "request": {
              "type": "Request",
              "kind": "Http",
              "inputs": {
                "schema": {
                  "type": "object",
                  "properties": {
                    "StoreId": {
                      "type": "string"
                    },
                    "createdDate": {
                      "type": "string"
                    },
                    "currency": {
                      "type": "string"
                    },
                    "customerId": {
                      "type": "string"
                    },
                    "customerName": {
                      "type": "string"
                    },
                    "dynamicProperties": {
                      "type": "array",
                      "items": {
                        "type": "object",
                        "properties": {
                          "name": {
                            "type": "string"
                          },
                          "values": {
                            "type": "array",
                            "items": {
                              "type": "object",
                              "properties": {
                                "value": {
                                  "type": "string"
                                }
                              },
                              "required": [
                                "value"
                              ]
                            }
                          }
                        },
                        "required": [
                          "name",
                          "values"
                        ]
                      }
                    },
                    "items": {
                      "type": "array",
                      "items": {
                        "type": "object",
                        "properties": {
                          "CatalogId": {
                            "type": "string"
                          },
                          "ProductId": {
                            "type": "string"
                          },
                          "currency": {
                            "type": "string"
                          },
                          "dynamicProperties": {
                            "type": "array",
                            "items": {
                              "type": "object",
                              "properties": {
                                "name": {
                                  "type": "string"
                                },
                                "values": {
                                  "type": "array",
                                  "items": {
                                    "type": "object",
                                    "properties": {
                                      "value": {
                                        "type": "string"
                                      }
                                    },
                                    "required": [
                                      "value"
                                    ]
                                  }
                                }
                              },
                              "required": [
                                "name",
                                "values"
                              ]
                            }
                          },
                          "name": {
                            "type": "string"
                          },
                          "price": {
                            "type": "number"
                          },
                          "quantity": {
                            "type": "integer"
                          },
                          "sku": {
                            "type": "string"
                          }
                        },
                        "required": [
                          "CatalogId",
                          "ProductId",
                          "currency",
                          "dynamicProperties",
                          "name",
                          "price",
                          "quantity",
                          "sku"
                        ]
                      }
                    },
                    "number": {
                      "type": "string"
                    },
                    "status": {
                      "type": "string"
                    }
                  }
                },
                "method": "POST"
              }
            }
          },
          "contentVersion": "1.0.0.0",
          "outputs": {}
        },
        "parameters": {
          "endpointPassword": {
            "value": "[parameters('passwordParam')]"
          },
          "endpointUsername": {
            "value": "[parameters('usernameParam')]"
          },
          "endpointUrl": {
            "value": "[parameters('urlParam')]"
          }
        }
      }
    }
  ],
  "outputs": {}
}